ninjacli/__init__.py
ninjacli/main.py
ninjacli/ai/__init__.py
ninjacli/ai/agent.py
ninjacli/ai/prompts.py
ninjacli/cli/__init__.py
ninjacli/cli/commands.py
ninjacli/cli/tools.py
ninjacli/core/__init__.py
ninjacli/core/message_history.py
ninjacli/ui/__init__.py
ninjacli/ui/intro.py
ninjacli/ui/logo.py
ninjacli/utils/__init__.py
ninjacli/utils/api_management.py
ninjacli/utils/validators.py
ninjacli-0.2.3.dist-info/licenses/LICENSE
ninjacli-0.2.3.dist-info/METADATA
ninjacli-0.2.3.dist-info/WHEEL
ninjacli-0.2.3.dist-info/entry_points.txt
ninjacli-0.2.3.dist-info/top_level.txt
ninjacli-0.2.3.dist-info/RECORD
