Metadata-Version: 2.4
Name: ninjacli
Version: 0.2.3
Summary: Ninja CLI is a high-performance terminal assistant that bridges the gap between natural language and system execution. Powered by state-of-the-art LLMs, it allows you to build, manage, and automate your development workflow using simple conversational commands.
Requires-Python: >=3.10
License-File: LICENSE
Requires-Dist: build>=1.4.0
Requires-Dist: openai>=2.15.0
Requires-Dist: pydantic>=2.12.5
Requires-Dist: python-dotenv>=1.2.1
Requires-Dist: readchar>=4.2.1
Requires-Dist: requests>=2.32.5
Requires-Dist: rich>=14.2.0
Requires-Dist: setuptools>=80.9.0
Requires-Dist: twine>=6.2.0
Requires-Dist: wheel>=0.45.1
Dynamic: license-file
Dynamic: requires-python
